Dubbo30Qianzhan/README.md
Dubbo30Qianzhan/__init__.py
Dubbo30Qianzhan/__main__.py
Dubbo30Qianzhan/file.pdf
Dubbo30Qianzhan/index.html
dubbo_3_0_qianzhan-2024.3.5.0.dist-info/METADATA
dubbo_3_0_qianzhan-2024.3.5.0.dist-info/WHEEL
dubbo_3_0_qianzhan-2024.3.5.0.dist-info/entry_points.txt
dubbo_3_0_qianzhan-2024.3.5.0.dist-info/top_level.txt
dubbo_3_0_qianzhan-2024.3.5.0.dist-info/RECORD
